tests/__init__.py
uac_cli/__init__.py
uac_cli/main.py
uac_cli/setup.py
uac_cli/commands/__init__.py
uac_cli/commands/agent.py
uac_cli/commands/agent_cluster.py
uac_cli/commands/audit.py
uac_cli/commands/bundle.py
uac_cli/commands/business_service.py
uac_cli/commands/calendar.py
uac_cli/commands/cluster_node.py
uac_cli/commands/config.py
uac_cli/commands/connection.py
uac_cli/commands/credential.py
uac_cli/commands/custom_day.py
uac_cli/commands/email_template.py
uac_cli/commands/ldap.py
uac_cli/commands/metric.py
uac_cli/commands/oauth_client.py
uac_cli/commands/oms_server.py
uac_cli/commands/property.py
uac_cli/commands/report.py
uac_cli/commands/script.py
uac_cli/commands/server_operation.py
uac_cli/commands/simulation.py
uac_cli/commands/system.py
uac_cli/commands/task.py
uac_cli/commands/task_instance.py
uac_cli/commands/trigger.py
uac_cli/commands/universal_event.py
uac_cli/commands/universal_event_template.py
uac_cli/commands/universal_template.py
uac_cli/commands/user.py
uac_cli/commands/user_group.py
uac_cli/commands/variable.py
uac_cli/commands/virtual_resource.py
uac_cli/commands/webhook.py
uac_cli/commands/workflow.py
uac_cli/utils/__init__.py
uac_cli/utils/config.py
uac_cli/utils/options.py
uac_cli/utils/process.py
uac_cli-1.0.1.dist-info/METADATA
uac_cli-1.0.1.dist-info/WHEEL
uac_cli-1.0.1.dist-info/entry_points.txt
uac_cli-1.0.1.dist-info/top_level.txt
uac_cli-1.0.1.dist-info/RECORD
