Metadata-Version: 2.1
Name: uac-cli
Version: 1.0.1
Summary: A CLI tool for executing commands against the Stonebranch UAC API
Author: Extensions Team
Author-email: Extensions Team <support@stonebranch.com>
Project-URL: Homepage, https://github.com
Project-URL: Issues, https://github.com
Project-URL: Documentation, https://readthedocs.io
Classifier: Programming Language :: Python :: 3
Classifier: License :: OSI Approved :: MIT License
Classifier: Operating System :: OS Independent
Requires-Python: >=3.7
Requires-Dist: PyYAML (==6.0.1)
Requires-Dist: click (==8.1.6)
Requires-Dist: jsonpath-ng (==1.5.3)
Requires-Dist: uac-api
